pandas_visual_analysis/__init__.py
pandas_visual_analysis/data_source.py
pandas_visual_analysis/layout.py
pandas_visual_analysis/version.py
pandas_visual_analysis/visual_analysis.py
pandas_visual_analysis/utils/__init__.py
pandas_visual_analysis/utils/column_store.py
pandas_visual_analysis/utils/config.py
pandas_visual_analysis/utils/util.py
pandas_visual_analysis/utils/validation.py
pandas_visual_analysis/widgets/__init__.py
pandas_visual_analysis/widgets/base_widget.py
pandas_visual_analysis/widgets/boxplot.py
pandas_visual_analysis/widgets/brush_summary.py
pandas_visual_analysis/widgets/histogram.py
pandas_visual_analysis/widgets/parcats.py
pandas_visual_analysis/widgets/parcoords.py
pandas_visual_analysis/widgets/registry.py
pandas_visual_analysis/widgets/scatter.py
pandas_visual_analysis/widgets/helpers/__init__.py
pandas_visual_analysis/widgets/helpers/multi_select.py
pandas_visual_analysis-0.0.4.dist-info/LICENSE
pandas_visual_analysis-0.0.4.dist-info/METADATA
pandas_visual_analysis-0.0.4.dist-info/WHEEL
pandas_visual_analysis-0.0.4.dist-info/top_level.txt
pandas_visual_analysis-0.0.4.dist-info/RECORD
