Metadata-Version: 2.1
Name: pandas-visual-analysis
Version: 0.0.4
Summary: A package for interactive visual analysis in Jupyter notebooks.
Home-page: https://github.com/meffmadd/pandas-visual-analysis
Author: Matthias Matt
Author-email: matthias.matt@student.tuwien.ac.at
License: MIT License
Keywords: pandas data-science visualization data-analysis brushing linked-brushing python jupyter ipython
Platform: UNKNOWN
Classifier: Development Status :: 4 - Beta
Classifier: Topic :: Scientific/Engineering :: Visualization
Classifier: License :: OSI Approved :: MIT License
Classifier: Environment :: Console
Classifier: Operating System :: OS Independent
Classifier: Intended Audience :: Science/Research
Classifier: Intended Audience :: Developers
Classifier: Intended Audience :: Financial and Insurance Industry
Classifier: Intended Audience :: Healthcare Industry
Classifier: Framework :: IPython
Classifier: Programming Language :: Python :: 3
Classifier: Programming Language :: Python :: 3.6
Classifier: Programming Language :: Python :: 3.7
Classifier: Programming Language :: Python :: 3.8
Requires-Python: >=3.6
Provides-Extra: notebook
